Metadata-Version: 2.1
Name: lmfit-slider
Version: 0.0.1
Summary: Make slider from lmfit model function and params
Home-page: https://github.com/bfichera/lmfit-slider
Author: Bryan Fichera
Author-email: bfichera@mit.edu
License: UNKNOWN
Platform: UNKNOWN
Classifier: Programming Language :: Python :: 3
Classifier: License :: OSI Approved :: MIT License
Classifier: Operating System :: OS Independent
License-File: LICENSE.txt
